dan_youtube_tutorial/__init__.py
dan_youtube_tutorial/dan_youtube_tutorial.py
dan_youtube_tutorial-0.0.1.dist-info/METADATA
dan_youtube_tutorial-0.0.1.dist-info/WHEEL
dan_youtube_tutorial-0.0.1.dist-info/top_level.txt
dan_youtube_tutorial-0.0.1.dist-info/RECORD
